persiantools/__init__.py
persiantools/characters.py
persiantools/digits.py
persiantools/jdatetime.py
persiantools/utils.py
persiantools-5.5.0.dist-info/licenses/LICENSE
persiantools-5.5.0.dist-info/METADATA
persiantools-5.5.0.dist-info/WHEEL
persiantools-5.5.0.dist-info/top_level.txt
persiantools-5.5.0.dist-info/RECORD
