Metadata-Version: 2.4
Name: persiantools
Version: 5.5.0
Summary: Jalali date and datetime with other tools
Author-email: Majid Hajiloo <majid.hajiloo@gmail.com>
License-Expression: MIT
Project-URL: Homepage, https://github.com/majiidd/persiantools
Project-URL: Source, https://github.com/majiidd/persiantools
Project-URL: Issues, https://github.com/majiidd/persiantools/issues
Keywords: jalali,shamsi,persian,digits,characters,converter,jalalidate,jalalidatetime,date,datetime,jdate,jdatetime,farsi
Classifier: Intended Audience :: Developers
Classifier: Natural Language :: Persian
Classifier: Operating System :: OS Independent
Classifier: Programming Language :: Python
Classifier: Programming Language :: Python :: 3
Classifier: Programming Language :: Python :: 3.9
Classifier: Programming Language :: Python :: 3.10
Classifier: Programming Language :: Python :: 3.11
Classifier: Programming Language :: Python :: 3.12
Classifier: Programming Language :: Python :: 3.13
Classifier: Programming Language :: Python :: 3.14
Classifier: Programming Language :: Python :: Implementation :: CPython
Classifier: Programming Language :: Python :: Implementation :: PyPy
Classifier: Topic :: Software Development
Classifier: Topic :: Software Development :: Libraries
Classifier: Topic :: Software Development :: Libraries :: Python Modules
Classifier: Topic :: Software Development :: Localization
Classifier: Topic :: Utilities
Requires-Python: >=3.9
License-File: LICENSE
Requires-Dist: tzdata; platform_system == "Windows"
Dynamic: license-file
